opencmd_tinge/__init__.py
opencmd_tinge/styled.py
opencmd_tinge/styles.py
opencmd_tinge-0.0.1.dist-info/licenses/LICENSE
opencmd_tinge-0.0.1.dist-info/METADATA
opencmd_tinge-0.0.1.dist-info/WHEEL
opencmd_tinge-0.0.1.dist-info/top_level.txt
opencmd_tinge-0.0.1.dist-info/RECORD
