Metadata-Version: 2.4
Name: opencmd-tinge
Version: 0.0.1
Summary: A terminal text styling library with chainable syntax
Author: OpenCmd
License-Expression: MIT
Project-URL: Homepage, https://github.com/opencommand/tinge-python
Keywords: cli,style,text,terminal,rich
Classifier: Programming Language :: Python :: 3
Classifier: Operating System :: OS Independent
Requires-Python: >=3.7
License-File: LICENSE
Requires-Dist: rich>=13.0.0
Dynamic: license-file
